{
  "report_type": "classify",
  "schema_version": "2.0.0",
  "generated_at": "2026-07-17T08:09:04Z",
  "lookback_days": 7,
  "window_start": "2026-07-10T08:09:04Z",
  "window_end": "2026-07-17T08:09:04Z",
  "metrics": {
    "total_classified": 3838,
    "classification_character_volume_proxy": 4541033,
    "relevance_rate": 0.7613340281396561,
    "average_confidence": 0.9646977592496091,
    "overall_topic_class_breakdown": {
      "core": 0.48697238144867117,
      "adjacent": 0.2743616466909849,
      "irrelevant": 0.23684210526315788,
      "unknown": 0.0018238665971860343
    }
  },
  "breakdowns": [
    {
      "source_id": 1,
      "classify_volume": 11,
      "classification_character_volume_proxy": 6611,
      "relevance_rate": 1.0,
      "average_confidence": 0.9672727272727273,
      "content_density_distribution": {
        "low": 0.18181818181818182,
        "medium": 0.8181818181818182,
        "high": 0.0
      },
      "topic_class_breakdown": {
        "core": 0.6363636363636364,
        "adjacent": 0.36363636363636365,
        "irrelevant": 0.0,
        "unknown": 0.0
      }
    },
    {
      "source_id": 2,
      "classify_volume": 8,
      "classification_character_volume_proxy": 96154,
      "relevance_rate": 1.0,
      "average_confidence": 0.9824999999999999,
      "content_density_distribution": {
        "low": 0.0,
        "medium": 0.0,
        "high": 1.0
      },
      "topic_class_breakdown": {
        "core": 1.0,
        "adjacent": 0.0,
        "irrelevant": 0.0,
        "unknown": 0.0
      }
    },
    {
      "source_id": 3,
      "classify_volume": 25,
      "classification_character_volume_proxy": 183960,
      "relevance_rate": 0.96,
      "average_confidence": 0.9608,
      "content_density_distribution": {
        "low": 0.0,
        "medium": 0.16,
        "high": 0.84
      },
      "topic_class_breakdown": {
        "core": 0.6,
        "adjacent": 0.36,
        "irrelevant": 0.04,
        "unknown": 0.0
      }
    },
    {
      "source_id": 4,
      "classify_volume": 25,
      "classification_character_volume_proxy": 101401,
      "relevance_rate": 0.96,
      "average_confidence": 0.982,
      "content_density_distribution": {
        "low": 0.04,
        "medium": 0.08,
        "high": 0.88
      },
      "topic_class_breakdown": {
        "core": 0.88,
        "adjacent": 0.08,
        "irrelevant": 0.0,
        "unknown": 0.04
      }
    },
    {
      "source_id": 5,
      "classify_volume": 24,
      "classification_character_volume_proxy": 239227,
      "relevance_rate": 1.0,
      "average_confidence": 0.975,
      "content_density_distribution": {
        "low": 0.041666666666666664,
        "medium": 0.08333333333333333,
        "high": 0.875
      },
      "topic_class_breakdown": {
        "core": 0.75,
        "adjacent": 0.25,
        "irrelevant": 0.0,
        "unknown": 0.0
      }
    },
    {
      "source_id": 6,
      "classify_volume": 25,
      "classification_character_volume_proxy": 5093,
      "relevance_rate": 0.92,
      "average_confidence": 0.9236,
      "content_density_distribution": {
        "low": 1.0,
        "medium": 0.0,
        "high": 0.0
      },
      "topic_class_breakdown": {
        "core": 0.6,
        "adjacent": 0.32,
        "irrelevant": 0.08,
        "unknown": 0.0
      }
    },
    {
      "source_id": 8,
      "classify_volume": 50,
      "classification_character_volume_proxy": 20956,
      "relevance_rate": 1.0,
      "average_confidence": 0.954,
      "content_density_distribution": {
        "low": 0.32,
        "medium": 0.68,
        "high": 0.0
      },
      "topic_class_breakdown": {
        "core": 0.8,
        "adjacent": 0.2,
        "irrelevant": 0.0,
        "unknown": 0.0
      }
    },
    {
      "source_id": 9,
      "classify_volume": 10,
      "classification_character_volume_proxy": 3574,
      "relevance_rate": 0.6,
      "average_confidence": 0.962,
      "content_density_distribution": {
        "low": 0.8,
        "medium": 0.2,
        "high": 0.0
      },
      "topic_class_breakdown": {
        "core": 0.0,
        "adjacent": 0.6,
        "irrelevant": 0.1,
        "unknown": 0.3
      }
    },
    {
      "source_id": 10,
      "classify_volume": 18,
      "classification_character_volume_proxy": 4642,
      "relevance_rate": 1.0,
      "average_confidence": 0.9555555555555555,
      "content_density_distribution": {
        "low": 0.7222222222222222,
        "medium": 0.2777777777777778,
        "high": 0.0
      },
      "topic_class_breakdown": {
        "core": 0.8333333333333334,
        "adjacent": 0.16666666666666666,
        "irrelevant": 0.0,
        "unknown": 0.0
      }
    },
    {
      "source_id": 11,
      "classify_volume": 10,
      "classification_character_volume_proxy": 4181,
      "relevance_rate": 1.0,
      "average_confidence": 0.959,
      "content_density_distribution": {
        "low": 0.7,
        "medium": 0.3,
        "high": 0.0
      },
      "topic_class_breakdown": {
        "core": 0.9,
        "adjacent": 0.1,
        "irrelevant": 0.0,
        "unknown": 0.0
      }
    },
    {
      "source_id": 12,
      "classify_volume": 11,
      "classification_character_volume_proxy": 4718,
      "relevance_rate": 1.0,
      "average_confidence": 0.9381818181818182,
      "content_density_distribution": {
        "low": 1.0,
        "medium": 0.0,
        "high": 0.0
      },
      "topic_class_breakdown": {
        "core": 0.9090909090909091,
        "adjacent": 0.09090909090909091,
        "irrelevant": 0.0,
        "unknown": 0.0
      }
    },
    {
      "source_id": 13,
      "classify_volume": 26,
      "classification_character_volume_proxy": 48360,
      "relevance_rate": 1.0,
      "average_confidence": 0.9526923076923077,
      "content_density_distribution": {
        "low": 0.038461538461538464,
        "medium": 0.8076923076923077,
        "high": 0.15384615384615385
      },
      "topic_class_breakdown": {
        "core": 0.6923076923076923,
        "adjacent": 0.3076923076923077,
        "irrelevant": 0.0,
        "unknown": 0.0
      }
    },
    {
      "source_id": 14,
      "classify_volume": 26,
      "classification_character_volume_proxy": 170227,
      "relevance_rate": 1.0,
      "average_confidence": 0.9796153846153846,
      "content_density_distribution": {
        "low": 0.0,
        "medium": 0.19230769230769232,
        "high": 0.8076923076923077
      },
      "topic_class_breakdown": {
        "core": 0.9615384615384616,
        "adjacent": 0.038461538461538464,
        "irrelevant": 0.0,
        "unknown": 0.0
      }
    },
    {
      "source_id": 15,
      "classify_volume": 6,
      "classification_character_volume_proxy": 1405,
      "relevance_rate": 1.0,
      "average_confidence": 0.9183333333333333,
      "content_density_distribution": {
        "low": 1.0,
        "medium": 0.0,
        "high": 0.0
      },
      "topic_class_breakdown": {
        "core": 0.0,
        "adjacent": 1.0,
        "irrelevant": 0.0,
        "unknown": 0.0
      }
    },
    {
      "source_id": 16,
      "classify_volume": 27,
      "classification_character_volume_proxy": 36649,
      "relevance_rate": 1.0,
      "average_confidence": 0.9555555555555556,
      "content_density_distribution": {
        "low": 0.0,
        "medium": 1.0,
        "high": 0.0
      },
      "topic_class_breakdown": {
        "core": 0.5925925925925926,
        "adjacent": 0.4074074074074074,
        "irrelevant": 0.0,
        "unknown": 0.0
      }
    },
    {
      "source_id": 17,
      "classify_volume": 25,
      "classification_character_volume_proxy": 114619,
      "relevance_rate": 1.0,
      "average_confidence": 0.966,
      "content_density_distribution": {
        "low": 0.0,
        "medium": 0.12,
        "high": 0.88
      },
      "topic_class_breakdown": {
        "core": 0.44,
        "adjacent": 0.56,
        "irrelevant": 0.0,
        "unknown": 0.0
      }
    },
    {
      "source_id": 18,
      "classify_volume": 10,
      "classification_character_volume_proxy": 4578,
      "relevance_rate": 1.0,
      "average_confidence": 0.943,
      "content_density_distribution": {
        "low": 0.8,
        "medium": 0.2,
        "high": 0.0
      },
      "topic_class_breakdown": {
        "core": 0.2,
        "adjacent": 0.8,
        "irrelevant": 0.0,
        "unknown": 0.0
      }
    },
    {
      "source_id": 19,
      "classify_volume": 62,
      "classification_character_volume_proxy": 119105,
      "relevance_rate": 0.9193548387096774,
      "average_confidence": 0.9603225806451613,
      "content_density_distribution": {
        "low": 0.20967741935483872,
        "medium": 0.5,
        "high": 0.2903225806451613
      },
      "topic_class_breakdown": {
        "core": 0.7903225806451613,
        "adjacent": 0.12903225806451613,
        "irrelevant": 0.06451612903225806,
        "unknown": 0.016129032258064516
      }
    },
    {
      "source_id": 20,
      "classify_volume": 16,
      "classification_character_volume_proxy": 11501,
      "relevance_rate": 0.4375,
      "average_confidence": 0.963125,
      "content_density_distribution": {
        "low": 0.375,
        "medium": 0.5,
        "high": 0.125
      },
      "topic_class_breakdown": {
        "core": 0.0625,
        "adjacent": 0.375,
        "irrelevant": 0.5625,
        "unknown": 0.0
      }
    },
    {
      "source_id": 21,
      "classify_volume": 35,
      "classification_character_volume_proxy": 11989,
      "relevance_rate": 0.37142857142857144,
      "average_confidence": 0.9654285714285714,
      "content_density_distribution": {
        "low": 0.2571428571428571,
        "medium": 0.7428571428571429,
        "high": 0.0
      },
      "topic_class_breakdown": {
        "core": 0.02857142857142857,
        "adjacent": 0.34285714285714286,
        "irrelevant": 0.6285714285714286,
        "unknown": 0.0
      }
    },
    {
      "source_id": 22,
      "classify_volume": 111,
      "classification_character_volume_proxy": 26082,
      "relevance_rate": 0.6396396396396397,
      "average_confidence": 0.95009009009009,
      "content_density_distribution": {
        "low": 0.6666666666666666,
        "medium": 0.3333333333333333,
        "high": 0.0
      },
      "topic_class_breakdown": {
        "core": 0.018018018018018018,
        "adjacent": 0.6216216216216216,
        "irrelevant": 0.36036036036036034,
        "unknown": 0.0
      }
    },
    {
      "source_id": 23,
      "classify_volume": 14,
      "classification_character_volume_proxy": 3824,
      "relevance_rate": 0.5,
      "average_confidence": 0.9635714285714286,
      "content_density_distribution": {
        "low": 0.6428571428571429,
        "medium": 0.35714285714285715,
        "high": 0.0
      },
      "topic_class_breakdown": {
        "core": 0.0,
        "adjacent": 0.5,
        "irrelevant": 0.5,
        "unknown": 0.0
      }
    },
    {
      "source_id": 24,
      "classify_volume": 25,
      "classification_character_volume_proxy": 17526,
      "relevance_rate": 0.64,
      "average_confidence": 0.9584,
      "content_density_distribution": {
        "low": 0.04,
        "medium": 0.96,
        "high": 0.0
      },
      "topic_class_breakdown": {
        "core": 0.0,
        "adjacent": 0.64,
        "irrelevant": 0.36,
        "unknown": 0.0
      }
    },
    {
      "source_id": 25,
      "classify_volume": 68,
      "classification_character_volume_proxy": 16356,
      "relevance_rate": 0.5735294117647058,
      "average_confidence": 0.9597058823529413,
      "content_density_distribution": {
        "low": 0.6176470588235294,
        "medium": 0.38235294117647056,
        "high": 0.0
      },
      "topic_class_breakdown": {
        "core": 0.014705882352941176,
        "adjacent": 0.5588235294117647,
        "irrelevant": 0.4264705882352941,
        "unknown": 0.0
      }
    },
    {
      "source_id": 26,
      "classify_volume": 146,
      "classification_character_volume_proxy": 42925,
      "relevance_rate": 0.1780821917808219,
      "average_confidence": 0.9799315068493151,
      "content_density_distribution": {
        "low": 0.4931506849315068,
        "medium": 0.5068493150684932,
        "high": 0.0
      },
      "topic_class_breakdown": {
        "core": 0.0,
        "adjacent": 0.1780821917808219,
        "irrelevant": 0.821917808219178,
        "unknown": 0.0
      }
    },
    {
      "source_id": 28,
      "classify_volume": 63,
      "classification_character_volume_proxy": 13391,
      "relevance_rate": 0.2698412698412698,
      "average_confidence": 0.9715873015873016,
      "content_density_distribution": {
        "low": 0.7301587301587301,
        "medium": 0.2698412698412698,
        "high": 0.0
      },
      "topic_class_breakdown": {
        "core": 0.015873015873015872,
        "adjacent": 0.25396825396825395,
        "irrelevant": 0.7301587301587301,
        "unknown": 0.0
      }
    },
    {
      "source_id": 29,
      "classify_volume": 6,
      "classification_character_volume_proxy": 30212,
      "relevance_rate": 0.5,
      "average_confidence": 0.9666666666666667,
      "content_density_distribution": {
        "low": 0.0,
        "medium": 0.0,
        "high": 1.0
      },
      "topic_class_breakdown": {
        "core": 0.0,
        "adjacent": 0.5,
        "irrelevant": 0.5,
        "unknown": 0.0
      }
    },
    {
      "source_id": 32,
      "classify_volume": 60,
      "classification_character_volume_proxy": 19783,
      "relevance_rate": 0.1,
      "average_confidence": 0.985,
      "content_density_distribution": {
        "low": 0.0,
        "medium": 0.9666666666666667,
        "high": 0.03333333333333333
      },
      "topic_class_breakdown": {
        "core": 0.0,
        "adjacent": 0.1,
        "irrelevant": 0.9,
        "unknown": 0.0
      }
    },
    {
      "source_id": 35,
      "classify_volume": 27,
      "classification_character_volume_proxy": 98027,
      "relevance_rate": 0.7407407407407407,
      "average_confidence": 0.9707407407407408,
      "content_density_distribution": {
        "low": 0.0,
        "medium": 0.0,
        "high": 1.0
      },
      "topic_class_breakdown": {
        "core": 0.0,
        "adjacent": 0.7407407407407407,
        "irrelevant": 0.25925925925925924,
        "unknown": 0.0
      }
    },
    {
      "source_id": 36,
      "classify_volume": 25,
      "classification_character_volume_proxy": 106859,
      "relevance_rate": 0.36,
      "average_confidence": 0.976,
      "content_density_distribution": {
        "low": 0.0,
        "medium": 0.0,
        "high": 1.0
      },
      "topic_class_breakdown": {
        "core": 0.0,
        "adjacent": 0.36,
        "irrelevant": 0.64,
        "unknown": 0.0
      }
    },
    {
      "source_id": 37,
      "classify_volume": 5,
      "classification_character_volume_proxy": 40489,
      "relevance_rate": 0.4,
      "average_confidence": 0.9800000000000001,
      "content_density_distribution": {
        "low": 0.0,
        "medium": 0.0,
        "high": 1.0
      },
      "topic_class_breakdown": {
        "core": 0.0,
        "adjacent": 0.4,
        "irrelevant": 0.6,
        "unknown": 0.0
      }
    },
    {
      "source_id": 38,
      "classify_volume": 7,
      "classification_character_volume_proxy": 27886,
      "relevance_rate": 0.7142857142857143,
      "average_confidence": 0.9742857142857143,
      "content_density_distribution": {
        "low": 0.0,
        "medium": 0.0,
        "high": 1.0
      },
      "topic_class_breakdown": {
        "core": 0.0,
        "adjacent": 0.7142857142857143,
        "irrelevant": 0.2857142857142857,
        "unknown": 0.0
      }
    },
    {
      "source_id": 39,
      "classify_volume": 25,
      "classification_character_volume_proxy": 86446,
      "relevance_rate": 0.24,
      "average_confidence": 0.9828,
      "content_density_distribution": {
        "low": 0.0,
        "medium": 0.0,
        "high": 1.0
      },
      "topic_class_breakdown": {
        "core": 0.0,
        "adjacent": 0.24,
        "irrelevant": 0.76,
        "unknown": 0.0
      }
    },
    {
      "source_id": 42,
      "classify_volume": 19,
      "classification_character_volume_proxy": 56774,
      "relevance_rate": 0.3157894736842105,
      "average_confidence": 0.973157894736842,
      "content_density_distribution": {
        "low": 0.0,
        "medium": 0.05263157894736842,
        "high": 0.9473684210526315
      },
      "topic_class_breakdown": {
        "core": 0.0,
        "adjacent": 0.3157894736842105,
        "irrelevant": 0.6842105263157895,
        "unknown": 0.0
      }
    },
    {
      "source_id": 43,
      "classify_volume": 12,
      "classification_character_volume_proxy": 34055,
      "relevance_rate": 0.25,
      "average_confidence": 0.9766666666666666,
      "content_density_distribution": {
        "low": 0.0,
        "medium": 0.08333333333333333,
        "high": 0.9166666666666666
      },
      "topic_class_breakdown": {
        "core": 0.0,
        "adjacent": 0.25,
        "irrelevant": 0.75,
        "unknown": 0.0
      }
    },
    {
      "source_id": 44,
      "classify_volume": 13,
      "classification_character_volume_proxy": 34783,
      "relevance_rate": 0.0,
      "average_confidence": 0.9876923076923076,
      "content_density_distribution": {
        "low": 0.0,
        "medium": 0.46153846153846156,
        "high": 0.5384615384615384
      },
      "topic_class_breakdown": {
        "core": 0.0,
        "adjacent": 0.0,
        "irrelevant": 1.0,
        "unknown": 0.0
      }
    },
    {
      "source_id": 45,
      "classify_volume": 5,
      "classification_character_volume_proxy": 14752,
      "relevance_rate": 0.0,
      "average_confidence": 0.986,
      "content_density_distribution": {
        "low": 0.0,
        "medium": 0.0,
        "high": 1.0
      },
      "topic_class_breakdown": {
        "core": 0.0,
        "adjacent": 0.0,
        "irrelevant": 1.0,
        "unknown": 0.0
      }
    },
    {
      "source_id": 46,
      "classify_volume": 4,
      "classification_character_volume_proxy": 13839,
      "relevance_rate": 0.0,
      "average_confidence": 0.99,
      "content_density_distribution": {
        "low": 0.0,
        "medium": 0.0,
        "high": 1.0
      },
      "topic_class_breakdown": {
        "core": 0.0,
        "adjacent": 0.0,
        "irrelevant": 1.0,
        "unknown": 0.0
      }
    },
    {
      "source_id": 47,
      "classify_volume": 102,
      "classification_character_volume_proxy": 104351,
      "relevance_rate": 0.12745098039215685,
      "average_confidence": 0.9850980392156863,
      "content_density_distribution": {
        "low": 0.0,
        "medium": 0.3627450980392157,
        "high": 0.6372549019607843
      },
      "topic_class_breakdown": {
        "core": 0.0,
        "adjacent": 0.12745098039215685,
        "irrelevant": 0.8725490196078431,
        "unknown": 0.0
      }
    },
    {
      "source_id": 48,
      "classify_volume": 24,
      "classification_character_volume_proxy": 104718,
      "relevance_rate": 0.4583333333333333,
      "average_confidence": 0.9700000000000001,
      "content_density_distribution": {
        "low": 0.0,
        "medium": 0.0,
        "high": 1.0
      },
      "topic_class_breakdown": {
        "core": 0.0,
        "adjacent": 0.4583333333333333,
        "irrelevant": 0.5416666666666666,
        "unknown": 0.0
      }
    },
    {
      "source_id": 51,
      "classify_volume": 1,
      "classification_character_volume_proxy": 1117,
      "relevance_rate": 1.0,
      "average_confidence": 0.98,
      "content_density_distribution": {
        "low": 0.0,
        "medium": 1.0,
        "high": 0.0
      },
      "topic_class_breakdown": {
        "core": 1.0,
        "adjacent": 0.0,
        "irrelevant": 0.0,
        "unknown": 0.0
      }
    },
    {
      "source_id": 52,
      "classify_volume": 5,
      "classification_character_volume_proxy": 1306,
      "relevance_rate": 1.0,
      "average_confidence": 0.952,
      "content_density_distribution": {
        "low": 0.6,
        "medium": 0.4,
        "high": 0.0
      },
      "topic_class_breakdown": {
        "core": 0.6,
        "adjacent": 0.4,
        "irrelevant": 0.0,
        "unknown": 0.0
      }
    },
    {
      "source_id": 53,
      "classify_volume": 35,
      "classification_character_volume_proxy": 18678,
      "relevance_rate": 0.9428571428571428,
      "average_confidence": 0.9382857142857142,
      "content_density_distribution": {
        "low": 0.17142857142857143,
        "medium": 0.8285714285714286,
        "high": 0.0
      },
      "topic_class_breakdown": {
        "core": 0.0,
        "adjacent": 0.9428571428571428,
        "irrelevant": 0.05714285714285714,
        "unknown": 0.0
      }
    },
    {
      "source_id": 56,
      "classify_volume": 9,
      "classification_character_volume_proxy": 2554,
      "relevance_rate": 1.0,
      "average_confidence": 0.9544444444444444,
      "content_density_distribution": {
        "low": 0.4444444444444444,
        "medium": 0.5555555555555556,
        "high": 0.0
      },
      "topic_class_breakdown": {
        "core": 1.0,
        "adjacent": 0.0,
        "irrelevant": 0.0,
        "unknown": 0.0
      }
    },
    {
      "source_id": 59,
      "classify_volume": 3,
      "classification_character_volume_proxy": 2354,
      "relevance_rate": 0.0,
      "average_confidence": 0.98,
      "content_density_distribution": {
        "low": 0.3333333333333333,
        "medium": 0.6666666666666666,
        "high": 0.0
      },
      "topic_class_breakdown": {
        "core": 0.0,
        "adjacent": 0.0,
        "irrelevant": 1.0,
        "unknown": 0.0
      }
    },
    {
      "source_id": 60,
      "classify_volume": 102,
      "classification_character_volume_proxy": 25662,
      "relevance_rate": 0.5098039215686274,
      "average_confidence": 0.9554901960784313,
      "content_density_distribution": {
        "low": 0.8431372549019608,
        "medium": 0.1568627450980392,
        "high": 0.0
      },
      "topic_class_breakdown": {
        "core": 0.00980392156862745,
        "adjacent": 0.5,
        "irrelevant": 0.49019607843137253,
        "unknown": 0.0
      }
    },
    {
      "source_id": 61,
      "classify_volume": 54,
      "classification_character_volume_proxy": 14128,
      "relevance_rate": 0.6296296296296297,
      "average_confidence": 0.9568518518518518,
      "content_density_distribution": {
        "low": 0.6296296296296297,
        "medium": 0.37037037037037035,
        "high": 0.0
      },
      "topic_class_breakdown": {
        "core": 0.037037037037037035,
        "adjacent": 0.5925925925925926,
        "irrelevant": 0.37037037037037035,
        "unknown": 0.0
      }
    },
    {
      "source_id": 62,
      "classify_volume": 56,
      "classification_character_volume_proxy": 13391,
      "relevance_rate": 0.25,
      "average_confidence": 0.9723214285714287,
      "content_density_distribution": {
        "low": 0.7857142857142857,
        "medium": 0.21428571428571427,
        "high": 0.0
      },
      "topic_class_breakdown": {
        "core": 0.017857142857142856,
        "adjacent": 0.23214285714285715,
        "irrelevant": 0.75,
        "unknown": 0.0
      }
    },
    {
      "source_id": 63,
      "classify_volume": 42,
      "classification_character_volume_proxy": 10603,
      "relevance_rate": 0.16666666666666666,
      "average_confidence": 0.9747619047619047,
      "content_density_distribution": {
        "low": 0.8095238095238095,
        "medium": 0.19047619047619047,
        "high": 0.0
      },
      "topic_class_breakdown": {
        "core": 0.023809523809523808,
        "adjacent": 0.14285714285714285,
        "irrelevant": 0.8333333333333334,
        "unknown": 0.0
      }
    },
    {
      "source_id": 64,
      "classify_volume": 39,
      "classification_character_volume_proxy": 17726,
      "relevance_rate": 0.6153846153846154,
      "average_confidence": 0.9569230769230769,
      "content_density_distribution": {
        "low": 0.1282051282051282,
        "medium": 0.8717948717948718,
        "high": 0.0
      },
      "topic_class_breakdown": {
        "core": 0.0,
        "adjacent": 0.6153846153846154,
        "irrelevant": 0.38461538461538464,
        "unknown": 0.0
      }
    },
    {
      "source_id": 65,
      "classify_volume": 25,
      "classification_character_volume_proxy": 14388,
      "relevance_rate": 0.92,
      "average_confidence": 0.9564,
      "content_density_distribution": {
        "low": 0.12,
        "medium": 0.88,
        "high": 0.0
      },
      "topic_class_breakdown": {
        "core": 0.56,
        "adjacent": 0.36,
        "irrelevant": 0.08,
        "unknown": 0.0
      }
    },
    {
      "source_id": 66,
      "classify_volume": 121,
      "classification_character_volume_proxy": 226451,
      "relevance_rate": 1.0,
      "average_confidence": 0.9778512396694214,
      "content_density_distribution": {
        "low": 0.008264462809917356,
        "medium": 0.7520661157024794,
        "high": 0.2396694214876033
      },
      "topic_class_breakdown": {
        "core": 0.8677685950413223,
        "adjacent": 0.1322314049586777,
        "irrelevant": 0.0,
        "unknown": 0.0
      }
    },
    {
      "source_id": 67,
      "classify_volume": 479,
      "classification_character_volume_proxy": 276918,
      "relevance_rate": 0.9979123173277662,
      "average_confidence": 0.9483089770354907,
      "content_density_distribution": {
        "low": 0.4384133611691023,
        "medium": 0.5594989561586639,
        "high": 0.0020876826722338203
      },
      "topic_class_breakdown": {
        "core": 0.8517745302713987,
        "adjacent": 0.14613778705636743,
        "irrelevant": 0.0,
        "unknown": 0.0020876826722338203
      }
    },
    {
      "source_id": 69,
      "classify_volume": 101,
      "classification_character_volume_proxy": 263147,
      "relevance_rate": 1.0,
      "average_confidence": 0.9677227722772277,
      "content_density_distribution": {
        "low": 0.0,
        "medium": 0.7623762376237624,
        "high": 0.2376237623762376
      },
      "topic_class_breakdown": {
        "core": 0.6633663366336634,
        "adjacent": 0.33663366336633666,
        "irrelevant": 0.0,
        "unknown": 0.0
      }
    },
    {
      "source_id": 70,
      "classify_volume": 481,
      "classification_character_volume_proxy": 679815,
      "relevance_rate": 0.9958419958419958,
      "average_confidence": 0.9688773388773388,
      "content_density_distribution": {
        "low": 0.158004158004158,
        "medium": 0.8378378378378378,
        "high": 0.004158004158004158
      },
      "topic_class_breakdown": {
        "core": 0.7796257796257796,
        "adjacent": 0.21621621621621623,
        "irrelevant": 0.004158004158004158,
        "unknown": 0.0
      }
    },
    {
      "source_id": 71,
      "classify_volume": 498,
      "classification_character_volume_proxy": 631214,
      "relevance_rate": 0.9979919678714859,
      "average_confidence": 0.9663253012048192,
      "content_density_distribution": {
        "low": 0.142570281124498,
        "medium": 0.8473895582329317,
        "high": 0.010040160642570281
      },
      "topic_class_breakdown": {
        "core": 0.7369477911646586,
        "adjacent": 0.26104417670682734,
        "irrelevant": 0.0,
        "unknown": 0.002008032128514056
      }
    },
    {
      "source_id": 72,
      "classify_volume": 355,
      "classification_character_volume_proxy": 195379,
      "relevance_rate": 1.0,
      "average_confidence": 0.9549859154929577,
      "content_density_distribution": {
        "low": 0.323943661971831,
        "medium": 0.676056338028169,
        "high": 0.0
      },
      "topic_class_breakdown": {
        "core": 0.5915492957746479,
        "adjacent": 0.4084507042253521,
        "irrelevant": 0.0,
        "unknown": 0.0
      }
    },
    {
      "source_id": 74,
      "classify_volume": 105,
      "classification_character_volume_proxy": 32898,
      "relevance_rate": 0.01904761904761905,
      "average_confidence": 0.9893333333333333,
      "content_density_distribution": {
        "low": 0.7047619047619048,
        "medium": 0.29523809523809524,
        "high": 0.0
      },
      "topic_class_breakdown": {
        "core": 0.009523809523809525,
        "adjacent": 0.009523809523809525,
        "irrelevant": 0.9809523809523809,
        "unknown": 0.0
      }
    },
    {
      "source_id": 75,
      "classify_volume": 3,
      "classification_character_volume_proxy": 589,
      "relevance_rate": 0.0,
      "average_confidence": 0.9899999999999999,
      "content_density_distribution": {
        "low": 0.6666666666666666,
        "medium": 0.3333333333333333,
        "high": 0.0
      },
      "topic_class_breakdown": {
        "core": 0.0,
        "adjacent": 0.0,
        "irrelevant": 1.0,
        "unknown": 0.0
      }
    },
    {
      "source_id": 78,
      "classify_volume": 80,
      "classification_character_volume_proxy": 23918,
      "relevance_rate": 0.0,
      "average_confidence": 0.9872500000000001,
      "content_density_distribution": {
        "low": 0.675,
        "medium": 0.325,
        "high": 0.0
      },
      "topic_class_breakdown": {
        "core": 0.0,
        "adjacent": 0.0,
        "irrelevant": 1.0,
        "unknown": 0.0
      }
    },
    {
      "source_id": 80,
      "classify_volume": 14,
      "classification_character_volume_proxy": 3072,
      "relevance_rate": 1.0,
      "average_confidence": 0.9807142857142858,
      "content_density_distribution": {
        "low": 1.0,
        "medium": 0.0,
        "high": 0.0
      },
      "topic_class_breakdown": {
        "core": 0.9285714285714286,
        "adjacent": 0.07142857142857142,
        "irrelevant": 0.0,
        "unknown": 0.0
      }
    },
    {
      "source_id": 81,
      "classify_volume": 5,
      "classification_character_volume_proxy": 1196,
      "relevance_rate": 1.0,
      "average_confidence": 0.986,
      "content_density_distribution": {
        "low": 1.0,
        "medium": 0.0,
        "high": 0.0
      },
      "topic_class_breakdown": {
        "core": 1.0,
        "adjacent": 0.0,
        "irrelevant": 0.0,
        "unknown": 0.0
      }
    },
    {
      "source_id": 82,
      "classify_volume": 2,
      "classification_character_volume_proxy": 430,
      "relevance_rate": 1.0,
      "average_confidence": 0.945,
      "content_density_distribution": {
        "low": 1.0,
        "medium": 0.0,
        "high": 0.0
      },
      "topic_class_breakdown": {
        "core": 0.0,
        "adjacent": 1.0,
        "irrelevant": 0.0,
        "unknown": 0.0
      }
    },
    {
      "source_id": 85,
      "classify_volume": 12,
      "classification_character_volume_proxy": 2071,
      "relevance_rate": 0.0,
      "average_confidence": 0.9899999999999999,
      "content_density_distribution": {
        "low": 1.0,
        "medium": 0.0,
        "high": 0.0
      },
      "topic_class_breakdown": {
        "core": 0.0,
        "adjacent": 0.0,
        "irrelevant": 1.0,
        "unknown": 0.0
      }
    }
  ]
}